basiccalculator/__init__.py
basiccalculator/basiccalculator.py
basiccalculator_ByteVolx-0.0.1.dist-info/LICENSE
basiccalculator_ByteVolx-0.0.1.dist-info/METADATA
basiccalculator_ByteVolx-0.0.1.dist-info/WHEEL
basiccalculator_ByteVolx-0.0.1.dist-info/top_level.txt
basiccalculator_ByteVolx-0.0.1.dist-info/RECORD
