Metadata-Version: 2.1
Name: basiccalculator-ByteVolx
Version: 0.0.1
Summary: this is my first module (basiccalculator). Made by ByteVolx
Home-page: https://github.com/pypa/sampleproject
Author: ByteVolx
License: UNKNOWN
Project-URL: Bug Tracker, https://github.com/pypa/sampleproject/issues
Platform: UNKNOWN
Classifier: Programming Language :: Python :: 3
Classifier: License :: OSI Approved :: MIT License
Classifier: Operating System :: OS Independent
Requires-Python: >=3.6
License-File: LICENSE
